nefino_geosync/__init__.py
nefino_geosync/access_rule_filter.py
nefino_geosync/api_client.py
nefino_geosync/compose_requests.py
nefino_geosync/config.py
nefino_geosync/download_analysis.py
nefino_geosync/download_completed_analyses.py
nefino_geosync/get_downloadable_analyses.py
nefino_geosync/graphql_errors.py
nefino_geosync/journal.py
nefino_geosync/layer_changelog.py
nefino_geosync/parse_args.py
nefino_geosync/run.py
nefino_geosync/schema.json
nefino_geosync/schema.py
nefino_geosync/session_logger.py
nefino_geosync/start_analyses.py
nefino_geosync/storage.py
nefino_geosync-0.2.3.dist-info/METADATA
nefino_geosync-0.2.3.dist-info/WHEEL
nefino_geosync-0.2.3.dist-info/entry_points.txt
nefino_geosync-0.2.3.dist-info/licenses/LICENSE
nefino_geosync-0.2.3.dist-info/RECORD
