Metadata-Version: 2.4
Name: nefino-geosync
Version: 0.2.3
Summary: Python package to access geographical data from Nefino.LI Geo
Project-URL: Application, https://nefino.li
Project-URL: API, https://api.nefino.li
Project-URL: Documentation, https://docs.nefino.li
Author-email: David Morris <david.morris@nefino.de>
Maintainer-email: Chris Stetter <chris.stetter@nefino.de>
License:                                  Apache License
License-File: LICENSE
Classifier: Development Status :: 4 - Beta
Classifier: Intended Audience :: Developers
Classifier: License :: OSI Approved :: Apache Software License
Classifier: Operating System :: OS Independent
Classifier: Programming Language :: Python :: 3
Classifier: Topic :: Scientific/Engineering :: GIS
Classifier: Topic :: Software Development :: Libraries
Requires-Python: >=3.8
Requires-Dist: graphql-core==3.2.4
Requires-Dist: prompt-toolkit==3.0.36
Requires-Dist: questionary==2.0.1
Requires-Dist: sgqlc==16.4
Requires-Dist: wcwidth==0.2.13
